client/__init__.py
client/add_contact.py
client/database.py
client/del_contact.py
client/main_window.py
client/main_window_conv.py
client/start_dialog.py
client/transport.py
common/__init__.py
common/decorators.py
common/descriptors.py
common/errors.py
common/metaclasses.py
common/utils.py
common/variables.py
unit_tests/__init__.py
unit_tests/test_client.py
unit_tests/test_server.py
unit_tests/test_utils.py
mess_clientVAG-0.0.1.dist-info/METADATA
mess_clientVAG-0.0.1.dist-info/WHEEL
mess_clientVAG-0.0.1.dist-info/top_level.txt
mess_clientVAG-0.0.1.dist-info/RECORD
