Metadata-Version: 2.1
Name: mess-clientVAG
Version: 0.0.1
Summary: mess_clientVAG
Author: Ganenko Vladislav
Author-email: vladislavchicheg@gmail.com
Requires-Dist: PyQt5
Requires-Dist: sqlalchemy
Requires-Dist: pycryptodome
Requires-Dist: pycryptodomex
